README.md
setup.py
uLTRA
modules/__init__.py
modules/align.py
modules/classify_alignment2.py
modules/classify_read_with_mams.py
modules/colinear_solver.py
modules/create_augmented_gene.py
modules/help_functions.py
modules/pc.py
modules/prefilter_genomic_reads.py
modules/range_query_max_search_tree.py
modules/sam_output.py
modules/seed_wrapper.py
modules/test_pc_multiprocess.py
ultra_bioinformatics.egg-info/PKG-INFO
ultra_bioinformatics.egg-info/SOURCES.txt
ultra_bioinformatics.egg-info/dependency_links.txt
ultra_bioinformatics.egg-info/requires.txt
ultra_bioinformatics.egg-info/top_level.txt