Metadata-Version: 2.1
Name: ultra-bioinformatics
Version: 0.1
Summary: Splice aligner of long transcriptomic reads to genome.
Home-page: https://github.com/ksahlin/uLTRA
Author: Kristoffer Sahlin
Author-email: ksahlin@math.su.se
Keywords: Oxford Nanopore transcript long read error correction
Classifier: Development Status :: 3 - Alpha
Classifier: Programming Language :: Python :: 3
Classifier: Programming Language :: Python :: 3.4
Classifier: Programming Language :: Python :: 3.5
Classifier: Programming Language :: Python :: 3.6
Classifier: Programming Language :: Python :: 3.7
Requires-Python: !=3.0.*, !=3.1.*, !=3.2.*, !=3.3.*, <4
